torchdyn/__init__.py
torchdyn/core/__init__.py
torchdyn/core/defunc.py
torchdyn/core/neuralde.py
torchdyn/core/problems.py
torchdyn/core/utils.py
torchdyn/datasets/__init__.py
torchdyn/datasets/static_datasets.py
torchdyn/models/README.md
torchdyn/models/__init__.py
torchdyn/models/cnf.py
torchdyn/models/energy.py
torchdyn/models/hybrid.py
torchdyn/nn/__init__.py
torchdyn/nn/galerkin.py
torchdyn/nn/node_layers.py
torchdyn/numerics/__init__.py
torchdyn/numerics/interpolators.py
torchdyn/numerics/odeint.py
torchdyn/numerics/sensitivity.py
torchdyn/numerics/solvers/_constants.py
torchdyn/numerics/solvers/hyper.py
torchdyn/numerics/solvers/ode.py
torchdyn/numerics/solvers/root.py
torchdyn/numerics/solvers/sde.py
torchdyn/numerics/solvers/templates.py
torchdyn/numerics/systems.py
torchdyn/numerics/utils.py
torchdyn/utils.py
torchdyn-1.0.6.dist-info/LICENSE
torchdyn-1.0.6.dist-info/METADATA
torchdyn-1.0.6.dist-info/WHEEL
torchdyn-1.0.6.dist-info/RECORD
